{
  "_fv": 79,
  "_type": "command",
  "definition": {
    "commandName": "f",
    "type": "STANDARD",
    "permissionLevel": "No requirement",
    "argsxml": "<xml xmlns=\"https://developers.google.com/blockly/xml\"><block type=\"args_start\" deletable=\"false\" x=\"40\" y=\"40\"><next><block type=\"literal\"><field name=\"name\">create</field><statement name=\"args\"><block type=\"string\"><field name=\"type\">word</field><field name=\"name\">id</field><statement name=\"args\"><block type=\"string\"><field name=\"type\">string</field><field name=\"name\">DisplayName</field><statement name=\"args\"><block type=\"call_procedure\"><field name=\"procedure\">FCreate</field></block></statement></block></statement></block></statement><next><block type=\"literal\"><field name=\"name\">f</field><statement name=\"args\"><block type=\"call_procedure\"><field name=\"procedure\">FF</field></block></statement></block></next></block></next></block></xml>"
  }
}